sb/__init__.py
sb/__main__.py
sb/api_client.py
sb/auditor.py
sb/bench.py
sb/cli.py
sb/config.py
sb/judge_rules.json
sb/loader.py
sb/output.py
sb/runner.py
sb/adapters/__init__.py
sb/docs/__init__.py
sb/docs/man.html
sb/evaluators/__init__.py
sb/evaluators/pattern.py
sb/reports/__init__.py
securitybench-0.2.13.dist-info/METADATA
securitybench-0.2.13.dist-info/WHEEL
securitybench-0.2.13.dist-info/entry_points.txt
securitybench-0.2.13.dist-info/licenses/LICENSE
securitybench-0.2.13.dist-info/RECORD
