Metadata-Version: 2.4
Name: securitybench
Version: 0.2.13
Summary: Security Bench - Security testing for LLM pipelines
Author: Security Bench Team
License: Elastic-2.0
License-File: LICENSE
Requires-Python: >=3.9
Requires-Dist: click>=8.0
Requires-Dist: httpx>=0.24
Requires-Dist: python-dotenv>=1.0
Requires-Dist: pyyaml>=6.0
Requires-Dist: rich>=13.0
Provides-Extra: dev
Requires-Dist: pytest-asyncio>=0.21; extra == 'dev'
Requires-Dist: pytest-cov>=4.0; extra == 'dev'
Requires-Dist: pytest>=7.0; extra == 'dev'
